weatherforecastcli/__init__.py
weatherforecastcli/config.py
weatherforecastcli/errors.py
weatherforecastcli/geocoding.py
weatherforecastcli/main.py
weatherforecastcli/openmeteo.py
weatherforecastcli/positionstack.py
weatherforecastcli/render.py
weatherforecastcli/utils.py
weatherforecastcli-0.3.2.dist-info/entry_points.txt
weatherforecastcli-0.3.2.dist-info/WHEEL
weatherforecastcli-0.3.2.dist-info/METADATA
weatherforecastcli-0.3.2.dist-info/RECORD
