Metadata-Version: 2.1
Name: weatherforecastcli
Version: 0.3.2
Summary: 
Author: Your Name
Author-email: you@example.com
Requires-Python: >=3.10,<4.0
Classifier: Programming Language :: Python :: 3
Classifier: Programming Language :: Python :: 3.10
Requires-Dist: pydantic (>=1.10.2,<2.0.0)
Requires-Dist: requests (>=2.28.1,<3.0.0)
Requires-Dist: typer[all] (>=0.7.0,<0.8.0)
Requires-Dist: tzdata (>=2022.6,<2023.0)
